{
    "boxShadow": "none",
    "iconSVG": "/static/media/icon.1a5defb3c19b4cac4a27829d1f979e4c.svg",
    "labelText": "Auto evaluate from:",
    "topRow": 64,
    "labelWidth": "15",
    "type": "SELECT_WIDGET",
    "serverSideFiltering": false,
    "defaultOptionValue": "{{ ((options, serverSideFiltering) => ( appsmith.store.editModalDetails[\"Auto Evaluate\"]))(SelectAutoEvaluateEdit.options, SelectAutoEvaluateEdit.serverSideFiltering) }}",
    "animateLoading": true,
    "leftColumn": 2,
    "dynamicBindingPathList": [
        {"key": "accentColor"},
        {"key": "borderRadius"},
        {"key": "defaultOptionValue"},
        {"key": "options"}
    ],
    "options": "{{dataServices.autoEvaluate()}}",
    "labelStyle": "BOLD",
    "placeholderText": "Select Auto evaluate from",
    "isDisabled": false,
    "isRequired": false,
    "dynamicHeight": "FIXED",
    "accentColor": "{{appsmith.theme.colors.primaryColor}}",
    "isVisible": true,
    "version": 1,
    "isLoading": false,
    "borderRadius": "{{appsmith.theme.borderRadius.appBorderRadius}}",
    "originalBottomRow": 110,
    "mobileBottomRow": 117,
    "widgetName": "SelectAutoEvaluateEdit",
    "isFilterable": true,
    "displayName": "Select",
    "searchTags": ["dropdown"],
    "bottomRow": 68,
    "parentRowSpace": 10,
    "hideCard": false,
    "mobileRightColumn": 22,
    "parentColumnSpace": 10.125,
    "dynamicTriggerPathList": [],
    "labelPosition": "Left",
    "key": "zf2a8x69bu",
    "labelTextSize": "0.875rem",
    "isDeprecated": false,
    "rightColumn": 61,
    "widgetId": "lr4kjrooey",
    "minWidth": 450,
    "parentId": "a13z0lz092",
    "labelAlignment": "left",
    "renderMode": "CANVAS",
    "mobileTopRow": 110,
    "responsiveBehavior": "fill",
    "originalTopRow": 106,
    "mobileLeftColumn": 2,
    "maxDynamicHeight": 9000,
    "minDynamicHeight": 4
}