{
    "mobileBottomRow": 5,
    "widgetName": "Text7",
    "displayName": "Text",
    "iconSVG": "/static/media/icon.97c59b523e6f70ba6f40a10fc2c7c5b5.svg",
    "searchTags": [
        "typography",
        "paragraph",
        "label"
    ],
    "topRow": 0,
    "bottomRow": 4,
    "type": "TEXT_WIDGET",
    "hideCard": false,
    "mobileRightColumn": 41,
    "animateLoading": true,
    "overflow": "NONE",
    "fontFamily": "{{appsmith.theme.fontFamily.appFont}}",
    "dynamicTriggerPathList": [],
    "leftColumn": 1,
    "dynamicBindingPathList": [
        {"key": "truncateButtonColor"},
        {"key": "fontFamily"},
        {"key": "borderRadius"}
    ],
    "shouldTruncate": false,
    "truncateButtonColor": "{{appsmith.theme.colors.primaryColor}}",
    "text": "Individual KPI",
    "key": "7kfkpn7vog",
    "isDeprecated": false,
    "rightColumn": 41,
    "textAlign": "LEFT",
    "dynamicHeight": "AUTO_HEIGHT",
    "widgetId": "x9m0t1g5d5",
    "minWidth": 450,
    "isVisible": true,
    "fontStyle": "BOLD",
    "textColor": "#231F20",
    "version": 1,
    "parentId": "7i3u75m5r9",
    "renderMode": "CANVAS",
    "isLoading": false,
    "mobileTopRow": 1,
    "responsiveBehavior": "fill",
    "borderRadius": "{{appsmith.theme.borderRadius.appBorderRadius}}",
    "mobileLeftColumn": 1,
    "maxDynamicHeight": 9000,
    "fontSize": "1.25rem",
    "minDynamicHeight": 4
}